spoofy_archiver/__init__.py
spoofy_archiver/__main__.py
spoofy_archiver/cli/__init__.py
spoofy_archiver/cli/main_interactive.py
spoofy_archiver/cli/main_noninteractive.py
spoofy_archiver/services/api/__init__.py
spoofy_archiver/services/api/constants.py
spoofy_archiver/services/api/main.py
spoofy_archiver/services/api_cache/__init__.py
spoofy_archiver/services/api_cache/main.py
spoofy_archiver/services/api_cache/models.py
spoofy_archiver/services/archiver/__init__.py
spoofy_archiver/services/archiver/constants.py
spoofy_archiver/services/archiver/main.py
spoofy_archiver/services/login/__init__.py
spoofy_archiver/services/login/authentication.py
spoofy_archiver/services/login/constants.py
spoofy_archiver/services/login/main.py
spoofy_archiver/services/login/models.py
spoofy_archiver/services/metadata/__init__.py
spoofy_archiver/services/metadata/models.py
spoofy_archiver/services/track_downloader/__init__.py
spoofy_archiver/services/track_downloader/main.py
spoofy_archiver/utils/__init__.py
spoofy_archiver/utils/constants.py
spoofy_archiver/utils/download_delayer.py
spoofy_archiver/utils/helpers.py
spoofy_archiver/utils/logger.py
mutagen/__init__.py
mutagen/_constants.py
mutagen/_file.py
mutagen/_iff.py
mutagen/_riff.py
mutagen/_tags.py
mutagen/_tools/__init__.py
mutagen/_tools/_util.py
mutagen/_tools/mid3cp.py
mutagen/_tools/mid3iconv.py
mutagen/_tools/mid3v2.py
mutagen/_tools/moggsplit.py
mutagen/_tools/mutagen_inspect.py
mutagen/_tools/mutagen_pony.py
mutagen/_util.py
mutagen/_vorbis.py
mutagen/aac.py
mutagen/ac3.py
mutagen/aiff.py
mutagen/apev2.py
mutagen/asf/__init__.py
mutagen/asf/_attrs.py
mutagen/asf/_objects.py
mutagen/asf/_util.py
mutagen/dsdiff.py
mutagen/dsf.py
mutagen/easyid3.py
mutagen/easymp4.py
mutagen/flac.py
mutagen/id3/__init__.py
mutagen/id3/_file.py
mutagen/id3/_frames.py
mutagen/id3/_id3v1.py
mutagen/id3/_specs.py
mutagen/id3/_tags.py
mutagen/id3/_util.py
mutagen/m4a.py
mutagen/monkeysaudio.py
mutagen/mp3/__init__.py
mutagen/mp3/_util.py
spoofy_archiver-1.0.8.dist-info/WHEEL
spoofy_archiver-1.0.8.dist-info/entry_points.txt
spoofy_archiver-1.0.8.dist-info/METADATA
spoofy_archiver-1.0.8.dist-info/RECORD
