Metadata-Version: 2.3
Name: spoofy-archiver
Version: 1.0.8
Summary: Archiver for popular streaming service Spoofy
Requires-Dist: colorama>=0.4.6
Requires-Dist: duckdb>=1.4.2
Requires-Dist: librespot>=0.0.10
Requires-Dist: pathvalidate>=3.3.1
Requires-Dist: pydantic>=2.12.4
Requires-Dist: python-dotenv>=1.1.1
Requires-Dist: requests>=2.32.5
Requires-Dist: spotipy>=2.25.1
Requires-Dist: tqdm>=4.67.1
Requires-Python: >=3.11
Project-URL: repository, https://github.com/kism/spoofy-archiver
